guyteub/__init__.py
guyteub/__main__.py
guyteub/activity_processor.py
guyteub/activity_visualizer.py
guyteub/app.py
guyteub/github_activity_api.py
guyteub/github_scrapper.py
guyteub-0.1.5.dist-info/licenses/LICENSE
guyteub-0.1.5.dist-info/METADATA
guyteub-0.1.5.dist-info/WHEEL
guyteub-0.1.5.dist-info/entry_points.txt
guyteub-0.1.5.dist-info/top_level.txt
guyteub-0.1.5.dist-info/RECORD
