Metadata-Version: 2.4
Name: guyteub
Version: 0.1.5
Summary: Outils pour afficher les stats GitHub dans un terminal
Home-page: https://github.com/votre-username/guyteub
Author: Baptiste
Author-email: 
License: MIT
Project-URL: Homepage, https://github.com/votre-username/guyteub
Classifier: Programming Language :: Python :: 3
Classifier: License :: OSI Approved :: MIT License
Classifier: Operating System :: OS Independent
Classifier: Development Status :: 3 - Alpha
Classifier: Intended Audience :: Developers
Requires-Python: >=3.6
License-File: LICENSE
Requires-Dist: requests
Requires-Dist: rich
Dynamic: home-page
Dynamic: license-file
Dynamic: requires-python
